{"singlePage": [], "startSite": "", "filingNum": "", "onePageListNum": 15, "commentLabelColor": "#006b75", "yearColorList": ["#bc4c00", "#0969da", "#1f883d", "#A333D0"], "i18n": "CN", "themeMode": "manual", "dayTheme": "light", "nightTheme": "dark", "urlMode": "pinyin", "script": "", "style": "", "head": "", "indexScript": "", "indexStyle": "", "bottomText": "", "showPostSource": 1, "iconList": {}, "UTC": 8, "rssSplit": "sentence", "exlink": {}, "needComment": 1, "allHead": "", "title": "Blog Title", "subTitle": "Blog description", "avatarUrl": "https://github.githubassets.com/favicons/favicon.svg", "GMEEK_VERSION": "last", "postListJson": {"P1": {"htmlDir": "docs/post/\ud83d\udca7 -liu-shui-bu-zheng-xian-\uff0c-zheng-de-shi-tao-tao-bu-jue.html", "labels": ["documentation"], "postTitle": "\ud83d\udca7 \u6d41\u6c34\u4e0d\u4e89\u5148\uff0c\u4e89\u7684\u662f\u6ed4\u6ed4\u4e0d\u7edd", "postUrl": "post/%F0%9F%92%A7%20-liu-shui-bu-zheng-xian-%EF%BC%8C-zheng-de-shi-tao-tao-bu-jue.html", "postSourceUrl": "https://github.com/sg6s/motto/issues/1", "commentNum": 0, "wordCount": 597, "description": "![\u5c71\u95f4\u6eaa\u6d41](https://images.pexels.com/photos/9758/nature-brook-creek-stream.jpg)\n*\u6e05\u6f88\u6eaa\u6d41\u7a7f\u8d8a\u5c71\u6da7 - \u6301\u7eed\u7684\u529b\u91cf*\n\n#### \ud83d\udcda \u6838\u5fc3\u8981\u4e49\uff1a\u957f\u671f\u4e3b\u4e49\n> **\u4e0d\u662f\u901f\u5ea6\u7684\u7ade\u8d5b\uff0c\u800c\u662f\u8010\u529b\u7684\u9a6c\u62c9\u677e**\n\n#### \ud83c\udfaf \u6df1\u5ea6\u89e3\u8bfb\n**\u957f\u671f\u601d\u7ef4\u7684\u4e09\u91cd\u5883\u754c\uff1a**\n1. **\u65f6\u95f4\u7ef4\u5ea6** - \u4ee5\u5341\u5e74\u4e3a\u5355\u4f4d\u601d\u8003\u4eba\u751f\n2. **\u4ef7\u503c\u7ef4\u5ea6** - \u4e13\u6ce8\u4e8e\u79ef\u7d2f\u771f\u6b63\u91cd\u8981\u7684\u4e1c\u897f\n3. **\u7cfb\u7edf\u7ef4\u5ea6** - \u6784\u5efa\u53ef\u6301\u7eed\u53d1\u5c55\u7684\u751f\u6d3b\u4f53\u7cfb\n\n**\u77ed\u671f\u4e3b\u4e49\u7684\u9677\u9631\uff1a**\n- \u274c \u8ffd\u6c42\u5373\u65f6\u6ee1\u8db3\n- \u274c \u76f2\u76ee\u8ddf\u98ce\u8ffd\u9010\u70ed\u70b9\n- \u274c \u4e3a\u77ed\u671f\u5229\u76ca\u727a\u7272\u957f\u671f\u4ef7\u503c\n\n#### \ud83d\udee0\ufe0f \u5b9e\u8df5\u6307\u5357\n**\u5efa\u7acb\u6301\u7eed\u7cfb\u7edf\u7684\u56db\u4e2a\u6b65\u9aa4\uff1a**\n\n| \u6b65\u9aa4 | \u5177\u4f53\u884c\u52a8 | \u68c0\u67e5\u6807\u51c6 |\n|-----|----------|----------|\n| \u8bbe\u8ba1\u7cfb\u7edf | \u5efa\u7acb\u6bcf\u65e5\u5fae\u4e60\u60ef | \u662f\u5426\u53ef\u6301\u7eed |\n| \u8bbe\u7f6e\u53cd\u9988 | \u5efa\u7acb\u8fdb\u5ea6\u8ffd\u8e2a | \u662f\u5426\u53ef\u8861\u91cf |\n| \u5b9a\u671f\u4f18\u5316 | \u6bcf\u5468\u590d\u76d8\u6539\u8fdb | \u662f\u5426\u5728\u8fdb\u6b65 |\n| \u957f\u671f\u575a\u6301 | \u5e74\u5ea6\u603b\u7ed3\u8c03\u6574 | \u662f\u5426\u8fbe\u76ee\u6807 |\n\n**\u4eca\u65e5\u884c\u52a8\u6e05\u5355\uff1a**\n- [ ] \u5217\u51fa3\u4e2a\u503c\u5f97\u957f\u671f\u6295\u5165\u7684\u9886\u57df\n- [ ] \u4e3a\u6bcf\u4e2a\u9886\u57df\u8bbe\u5b9a\u6bcf\u65e5\u6700\u5c0f\u884c\u52a8\n- [ ] \u5efa\u7acb\u8fdb\u5ea6\u8ffd\u8e2a\u8bb0\u5f55\u8868\n\n#### \ud83c\udf08 \u4eca\u65e5\u601d\u8003\n> '\u5982\u679c\u6211\u80fd\u575a\u6301\u505a\u4e00\u4ef6\u4e8b\u5341\u5e74\uff0c\u90a3\u4f1a\u662f\u4ec0\u4e48\u4e8b\uff1f'\n\n---\u3002", "top": 0, "createdAt": 1760862230, "style": "", "script": "", "head": "", "ogImage": "https://github.githubassets.com/favicons/favicon.svg", "createdDate": "2025-10-19", "dateLabelColor": "#0969da"}, "P2": {"htmlDir": "docs/post/\ud83c\udf33 -zhong-shu-zui-hao-de-shi-jian-shi-shi-nian-qian-\uff0c-qi-ci-shi-xian-zai.html", "labels": ["documentation"], "postTitle": "\ud83c\udf33 \u79cd\u6811\u6700\u597d\u7684\u65f6\u95f4\u662f\u5341\u5e74\u524d\uff0c\u5176\u6b21\u662f\u73b0\u5728", "postUrl": "post/%F0%9F%8C%B3%20-zhong-shu-zui-hao-de-shi-jian-shi-shi-nian-qian-%EF%BC%8C-qi-ci-shi-xian-zai.html", "postSourceUrl": "https://github.com/sg6s/motto/issues/2", "commentNum": 0, "wordCount": 408, "description": "![\u690d\u6811\u9020\u6797](https://images.pexels.com/photos/34354341/pexels-photo-34354341.jpeg)\n*\u53cc\u624b\u6367\u8d77\u6811\u82d7 - \u884c\u52a8\u7684\u5f00\u59cb*\n\n#### \ud83d\udcda \u6838\u5fc3\u8981\u4e49\uff1a\u7acb\u5373\u884c\u52a8\n> **\u6bcf\u4e00\u4e2a\u2018\u73b0\u5728\u2019\u90fd\u662f\u65b0\u7684\u2018\u5341\u5e74\u524d\u2019**\n\n#### \ud83c\udfaf \u6df1\u5ea6\u89e3\u8bfb\n```mermaid\ngraph LR\n    A[\u60f3\u505a\u7684\u4e8b] --> B{\u7acb\u5373\u5f00\u59cb}\n    B --> C[\u4eca\u5929\u884c\u52a8]\n    B --> D[\u7b49\u5f85\u660e\u5929]\n    C --> E[\u53d6\u5f97\u8fdb\u5c55]\n    D --> F[\u6c38\u8fdc\u62d6\u5ef6]\n\ud83d\udee0\ufe0f \u5b9e\u8df5\u6307\u5357\n\u7acb\u5373\u542f\u52a8\u4e09\u6b65\u6cd5\uff1a\n\n\ud83d\ude80 \u7834\u9664\u5fc3\u7406\u969c\u788d\n\n\u63a5\u53d7\u4e0d\u5b8c\u7f8e\n\n\u964d\u4f4e\u542f\u52a8\u95e8\u69db\n\n\u8bbe\u5b9a\u6700\u5c0f\u76ee\u6807\n\n\ud83d\udd25 \u5efa\u7acb\u884c\u52a8\u52a8\u91cf\n\n5\u5206\u949f\u8d77\u6b65\u6cd5\u5219\n\n\u521b\u9020\u7269\u7406\u73af\u5883\n\n\u83b7\u53d6\u5373\u65f6\u53cd\u9988\n\n\ud83d\udcc8 \u6301\u7eed\u4f18\u5316\u8fed\u4ee3\n\n\u6bcf\u65e5\u5fae\u8c03\n\n\u6bcf\u5468\u590d\u76d8\n\n\u6bcf\u6708\u5347\u7ea7\n\n\ud83c\udf08 \u4eca\u65e5\u601d\u8003\n\u201c\u54ea\u4e2a\u62d6\u5ef6\u5df2\u4e45\u7684\u8ba1\u5212\uff0c\u4eca\u5929\u53ef\u4ee5\u5f00\u59cb\u7b2c\u4e00\u6b65\uff1f\u201d\u3002", "top": 0, "createdAt": 1760862397, "style": "", "script": "", "head": "", "ogImage": "https://github.githubassets.com/favicons/favicon.svg", "createdDate": "2025-10-19", "dateLabelColor": "#0969da"}, "P3": {"htmlDir": "docs/post/\ud83e\ude9e -jun-zi-qiu-zhu-ji-\uff0c-xiao-ren-qiu-zhu-ren.html", "labels": ["documentation"], "postTitle": "\ud83e\ude9e \u541b\u5b50\u6c42\u8bf8\u5df1\uff0c\u5c0f\u4eba\u6c42\u8bf8\u4eba", "postUrl": "post/%F0%9F%AA%9E%20-jun-zi-qiu-zhu-ji-%EF%BC%8C-xiao-ren-qiu-zhu-ren.html", "postSourceUrl": "https://github.com/sg6s/motto/issues/3", "commentNum": 0, "wordCount": 354, "description": "![\u955c\u4e2d\u81ea\u89c2](https://images.pexels.com/photos/774866/pexels-photo-774866.jpeg)\n\u955c\u4e2d\u81ea\u89c2 - \u5185\u5728\u7684\u529b\u91cf\n\n\ud83d\udcda \u6838\u5fc3\u8981\u4e49\uff1a\u81ea\u6211\u8d1f\u8d23\n\u751f\u547d\u7684\u65b9\u5411\u76d8\uff0c\u59cb\u7ec8\u5728\u81ea\u5df1\u624b\u4e2d\n\n\ud83c\udfaf \u6df1\u5ea6\u89e3\u8bfb\n\u4e09\u4e2a\u8d23\u4efb\u5c42\u6b21\uff1a\n\n\u57fa\u7840\u5c42 - \u60c5\u7eea\u8d23\u4efb\n\ntext\n\ud83d\udcad \u60f3\u6cd5 \u2192 \ud83c\udfad \u60c5\u7eea \u2192 \ud83c\udfac \u884c\u4e3a\n\u638c\u63e1\u601d\u7ef4\uff0c\u5c31\u638c\u63e1\u4e86\u4e00\u5207\n\u4e2d\u95f4\u5c42 - \u884c\u52a8\u8d23\u4efb\n\n\u4e3b\u52a8\u89e3\u51b3\u95ee\u9898\n\n\u5bfb\u6c42\u8d44\u6e90\u652f\u6301\n\n\u627f\u62c5\u9009\u62e9\u540e\u679c\n\n\u9ad8\u7ea7\u5c42 - \u6210\u957f\u8d23\u4efb\n\n\u6301\u7eed\u5b66\u4e60\u8fdb\u5316\n\n\u7a81\u7834\u81ea\u6211\u5c40\u9650\n\n\u521b\u9020\u4e2a\u4eba\u4ef7\u503c\n\n\ud83d\udee0\ufe0f \u5b9e\u8df5\u6307\u5357\n\u6bcf\u65e5\u4e09\u7701\uff1a\n\n\u2705 \u4eca\u5929\u54ea\u4e9b\u4e8b\u60c5\u6211\u53ef\u4ee5\u505a\u5f97\u66f4\u597d\uff1f\n\n\u2705 \u9047\u5230\u56f0\u96be\u65f6\uff0c\u6211\u662f\u5426\u5148\u60f3\u89e3\u51b3\u529e\u6cd5\uff1f\n\n\u2705 \u6211\u662f\u5426\u4e3a\u60f3\u8981\u7684\u751f\u6d3b\u4ed8\u51fa\u4e86\u8db3\u591f\u52aa\u529b\uff1f\n\n\ud83c\udf08 \u4eca\u65e5\u601d\u8003\n\u201c\u5728\u5f53\u524d\u7684\u6311\u6218\u4e2d\uff0c\u6211\u80fd\u63a7\u5236\u7684\u56e0\u7d20\u6709\u54ea\u4e9b\uff1f\u201d\u3002", "top": 0, "createdAt": 1760862510, "style": "", "script": "", "head": "", "ogImage": "https://github.githubassets.com/favicons/favicon.svg", "createdDate": "2025-10-19", "dateLabelColor": "#0969da"}}, "singeListJson": {}, "labelColorDict": {"bug": "#d73a4a", "documentation": "#0075ca", "duplicate": "#cfd3d7", "enhancement": "#a2eeef", "good first issue": "#7057ff", "help wanted": "#008672", "invalid": "#e4e669", "question": "#d876e3", "wontfix": "#ffffff"}, "displayTitle": "Blog Title", "faviconUrl": "https://github.githubassets.com/favicons/favicon.svg", "ogImage": "https://github.githubassets.com/favicons/favicon.svg", "primerCSS": "<link href='https://mirrors.sustech.edu.cn/cdnjs/ajax/libs/Primer/21.0.7/primer.css' rel='stylesheet' />", "homeUrl": "https://sg6s.github.io/motto", "prevUrl": "disabled", "nextUrl": "disabled"}